LICENSE
event_history/__init__.py
event_history/generator.py
event_history/interfaces.py
event_history/pyproject.toml
event_history-0.1.1.dist-info/LICENSE
event_history-0.1.1.dist-info/WHEEL
event_history-0.1.1.dist-info/METADATA
event_history-0.1.1.dist-info/RECORD
