Metadata-Version: 2.1
Name: event-history
Version: 0.1.1
Summary: A minimal library to work with versioned events in atomic database transactions.
Home-page: https://github.com/tjgurwara99/event-history
License: Apache-2.0
Author: Taj
Author-email: tjgurwara99@gmail.com
Requires-Python: >=3.9,<4.0
Classifier: License :: OSI Approved :: Apache Software License
Classifier: Programming Language :: Python :: 3
Classifier: Programming Language :: Python :: 3.10
Classifier: Programming Language :: Python :: 3.9
Project-URL: Repository, https://github.com/tjgurwara99/event-history
